indox_client/__init__.py
indox_client/_base.py
indox_client/_client.py
indox_client/_exceptions.py
indox_client/_version.py
indox_client/resources/__init__.py
indox_client/resources/fonts/conversions.py
indox_client/resources/fonts/fonts.py
indox_client/resources/fonts/formats.py
indox_client-0.2.3.dist-info/licenses/LICENSE
indox_client-0.2.3.dist-info/METADATA
indox_client-0.2.3.dist-info/WHEEL
indox_client-0.2.3.dist-info/top_level.txt
indox_client-0.2.3.dist-info/RECORD
