Metadata-Version: 2.4
Name: indox-client
Version: 0.2.3
Summary: Python SDK for the Indox media and document conversion services.
Author-email: Indox <support@indox.org>
License-Expression: LicenseRef-Proprietary
Project-URL: Homepage, https://indox.org
Project-URL: Documentation, https://docs.indox.org
Project-URL: Repository, https://github.com/indox-org/indox_client
Project-URL: Issues, https://github.com/indox-org/indox_client/issues
Keywords: indox,document-conversion,media-conversion,sdk,api-client
Classifier: Development Status :: 4 - Beta
Classifier: Intended Audience :: Developers
Classifier: Programming Language :: Python :: 3
Classifier: Programming Language :: Python :: 3.9
Classifier: Programming Language :: Python :: 3.10
Classifier: Programming Language :: Python :: 3.11
Classifier: Programming Language :: Python :: 3.12
Classifier: Topic :: Software Development :: Libraries :: Python Modules
Requires-Python: >=3.9
License-File: LICENSE
Requires-Dist: requests>=2.28.0
Provides-Extra: dev
Requires-Dist: pytest>=7.0; extra == "dev"
Requires-Dist: pytest-cov>=4.0; extra == "dev"
Requires-Dist: responses>=0.23.0; extra == "dev"
Requires-Dist: ruff>=0.1.0; extra == "dev"
Requires-Dist: mypy>=1.0; extra == "dev"
Requires-Dist: types-requests>=2.28; extra == "dev"
Dynamic: license-file
